frontpy/__init__.py
frontpy/calc_tfp.py
frontpy/cli.py
frontpy/color_palette.py
frontpy/download_data.py
frontpy/front_ident.py
frontpy/main.py
frontpy/make_gif.py
frontpy/plot_fronts.py
frontpy/utils.py
frontpy/resources/IR_colormap.cpt
frontpy-0.1.14.dist-info/LICENSE
frontpy-0.1.14.dist-info/METADATA
frontpy-0.1.14.dist-info/WHEEL
frontpy-0.1.14.dist-info/entry_points.txt
frontpy-0.1.14.dist-info/top_level.txt
frontpy-0.1.14.dist-info/RECORD
